jetpack/__init__.py
jetpack/_utils.py
jetpack/cmd/__init__.py
jetpack/cmd/_cron.py
jetpack/cmd/_params.py
jetpack/cmd/_root.py
jetpack/cmd/_util.py
jetpack/config/__init__.py
jetpack/config/_instrumentation.py
jetpack/config/_k8s.py
jetpack/config/_namespace.py
jetpack/config/_symbols.py
jetpack/core/__init__.py
jetpack/core/_errors.py
jetpack/core/_interface.py
jetpack/core/_jetpack_client.py
jetpack/core/_jetroutine.py
jetpack/core/_task.py
jetpack/cron.py
jetpack/errors/__init__.py
jetpack/proto/runtime/v1alpha1/app_pb2.py
jetpack/proto/runtime/v1alpha1/app_pb2.pyi
jetpack/proto/runtime/v1alpha1/app_pb2_grpc.py
jetpack/proto/runtime/v1alpha1/app_pb2_grpc.pyi
jetpack/proto/runtime/v1alpha1/jetworker_pb2.py
jetpack/proto/runtime/v1alpha1/jetworker_pb2.pyi
jetpack/proto/runtime/v1alpha1/jetworker_pb2_grpc.py
jetpack/proto/runtime/v1alpha1/jetworker_pb2_grpc.pyi
jetpack/proto/runtime/v1alpha1/remote_pb2.py
jetpack/proto/runtime/v1alpha1/remote_pb2.pyi
jetpack/proto/runtime/v1alpha1/remote_pb2_grpc.py
jetpack/proto/runtime/v1alpha1/remote_pb2_grpc.pyi
jetpack/proto/runtime/v1alpha1/task_pb2.py
jetpack/proto/runtime/v1alpha1/task_pb2.pyi
jetpack/proto/runtime/v1alpha1/task_pb2_grpc.py
jetpack/proto/runtime/v1alpha1/task_pb2_grpc.pyi
jetpack/py.typed
jetpack/runtime/__init__.py
jetpack/runtime/_client.py
jetpack/runtime/_errors.py
jetpack/runtime/_interceptor.py
jetpack/runtime/_local.py
jetpack/server/_server.py
jetpack/util/__init__.py
jetpack/util/_jetpickle.py
jetpack/util/network/__init__.py
jetpack/util/network/_codec.py
jetpack_io-0.5.1.dev202208201660993532.dist-info/entry_points.txt
jetpack_io-0.5.1.dev202208201660993532.dist-info/WHEEL
jetpack_io-0.5.1.dev202208201660993532.dist-info/METADATA
jetpack_io-0.5.1.dev202208201660993532.dist-info/RECORD
